{"title":"NorthPole Entertainment - Stepmom s Forbidden Fantasies XXX DVDR","uid":15397815,"size":1144251416,"categoryP":"porn","categoryS":"movies","magnet":"?xt=urn:btih:06843bb11a767e3acca2929e59ff223855545273&amp;dn=NorthPole+Entertainment+-+Stepmom+s+Forbidden+Fantasies+XXX+DVDR&amp;tr=udp%3A%2F%2Ftracker.leechers-paradise.org%3A6969&amp;tr=udp%3A%2F%2Fzer0day.ch%3A1337&amp;tr=udp%3A%2F%2Fopen.demonii.com%3A1337&amp;tr=udp%3A%2F%2Ftracker.coppersurfer.tk%3A6969&amp;tr=udp%3A%2F%2Fexodus.desync.com%3A6969","seeders":2,"leechers":1,"uploader":"SudoSu","files":1,"time":1469413811,"description":"http://youpornbook.com\r\n\r\n-------------------------\r\n ... : Screenshots : ... \r\n-------------------------\r\n \nhttp://imagep2p.com/?v=988898 \nhttp://imagep2p.com/?g=149808\r\n\r\n-------------------------\r\n ... : Description : ... \r\n-------------------------\r\n\r\nNorthPole Entertainment - Stepmom s Forbidden Fantasies XXX DVDRip\r\n\r\nMore exclusive porn at:  https://thepiratebay.se/user/SudoSu/","torrent":{"xt":"urn:btih:06843bb11a767e3acca2929e59ff223855545273","amp;dn":"NorthPole+Entertainment+-+Stepmom+s+Forbidden+Fantasies+XXX+DVDR","amp;tr":["udp%3A%2F%2Ftracker.leechers-paradise.org%3A6969","udp%3A%2F%2Fzer0day.ch%3A1337","udp%3A%2F%2Fopen.demonii.com%3A1337","udp%3A%2F%2Ftracker.coppersurfer.tk%3A6969","udp%3A%2F%2Fexodus.desync.com%3A6969"],"infoHash":"06843bb11a767e3acca2929e59ff223855545273","infoHashBuffer":{"type":"Buffer","data":[6,132,59,177,26,118,126,58,204,162,146,158,89,255,34,56,85,84,82,115]},"announce":[],"urlList":[]}}