{"title":"VA-This_Is_The_Sound_Of_Dubstep_Vol_2-2CD-2012-wAx-JKoop","uid":7686607,"size":222551758,"categoryP":"audio","categoryS":"music","magnet":"?xt=urn:btih:06d5dd4fd66429a09da7cd59877ea47eb3f4a073&amp;dn=VA-This_Is_The_Sound_Of_Dubstep_Vol_2-2CD-2012-wAx-JKoop&amp;tr=udp%3A%2F%2Ftracker.openbittorrent.com%3A80&amp;tr=udp%3A%2F%2Fopen.demonii.com%3A1337&amp;tr=udp%3A%2F%2Ftracker.coppersurfer.tk%3A6969&amp;tr=udp%3A%2F%2Fexodus.desync.com%3A6969","seeders":2,"leechers":0,"uploader":"jmz619","files":6,"time":1348964782,"description":"Ferrex&lt;SAC&gt;\n\n[ wAx iS PROUD TO PRESENT TO YOU\n                                                          wAx!\nVA - This Is The Sound Of Dubstep Vol 2-2CD\n\n[ RELEASE iNFORMATiON ]\n\nRELEASE DATE..[ Sep 29 - 2012\nRELEASE SiZE..[ 213.19 Mb\n# OF FiLES....[ 2\n\nQUALiTY.......[ 254 kBit/s\nUSED ENCODER..[ LAME3.98r\n\nGENRE.........[ Electronic\nYEAR..........[ 2012\nALBUM.........[ This Is The Sound Of Dubstep Vol 2-2CD\nARTiST(S).....[ VA\nLABEL.........[ Cloud 9 Music\n\n[ TRACKS ]\n\nNR - TiTLE ...                                                TiME.\n\n[ 101-va-this is the sound of dubstep vol 2 cd1              ] [58:16]\n[ 201-va-this is the sound of dubstep vol 2 cd2              ] [59:51]\n\n.x [ PLAY-TiME [118:08] -*- TOTAL TRACKS [02] ] x.\n\n[ TRACK LiST ]\n\nCD 1:\n\n01. Noisia ft Foreign Beggars - Shellshock\n02. Tritonal ft Cristina Soto - Still With Me (Seven Lions\n    Remix)\n03. Virtual Riot ft Amba Shepherd - Superhuman\n04. Paul Thomas - Buzz Killington (Funkagenda Remix)\n05. Dada Life - Kick Out The Epic Motherfucker (Datsik Remix)\n06. Excision &amp; Datsik - 8 Bit Superhero (Eptic Remix)\n07. Sharon Doorson - Fail In Love (TVDS Remix)\n08. Hardwell - Spaceman (Drown The Fish Remix)\n09. Foreign Beggars ft D.Ablo - Anywhere\n10. Dank - Blow Me\n11. Roll Deep - Picture Perfect (Cutline Remix)\n12. Matt Darey &amp; Aeron Aether ft Cath Porter - Blossom &amp; Decay\n13. Protohype &amp; Init - Bombs Away (Kezwik Remix)\n14. Perky &amp; Ashman - Good Lovin (Maduk Remix)\n15. Sharam Jey ft Nik Valentino - The More That I Do (Rico\n    Tubbs Remix)\n16. Paul Oakenfold ft J. Hart - Surrender (Traydkraft Remix)\n17. Franky Nuts - Bang Like This\n\nCD 2:\n\n01. Noisia - Alpha Centauri (Receptor Remix)\n02. Excision ft Savy - Sleepless (Xilent Remix)\n03. Foreign Beggars - Apex\n04. Metzo, Yeo - Devil (Calvertron Remix)\n05. Jantsen &amp; AFK - Shake That\n06. Buraka Som Sistema - Hangover (BaBaBa) (Caspa Remix)\n07. Brian Cameron - Serotonin Syndrome (Eshericks Remix)\n08. Juventa - Knockdown\n09. Franky Nuts ft Skinto &amp; Don De Baron - Animal\n10. Zinnat - The Future\n11. Emma Hewitt - Rewind (KATFYR Remix)\n12. Utah Saints vs Drumsound &amp; Bassline Smith - What Can You Do\n    For Me (Tantrum Desire Remix)\n13. Jess Mills - Live For What I'd Die For (Distance Remix)\n14. Hectic ft Leighanna - Believe And Achieve (Sound Avtar\n    Remix)\n15. Posij - Empty Lungs\n16. Justin Michael ft AJ from Saint Motel - Eyes Closed (Flinch\n    Remix)","torrent":{"xt":"urn:btih:06d5dd4fd66429a09da7cd59877ea47eb3f4a073","amp;dn":"VA-This_Is_The_Sound_Of_Dubstep_Vol_2-2CD-2012-wAx-JKoop","amp;tr":["udp%3A%2F%2Ftracker.openbittorrent.com%3A80","udp%3A%2F%2Fopen.demonii.com%3A1337","udp%3A%2F%2Ftracker.coppersurfer.tk%3A6969","udp%3A%2F%2Fexodus.desync.com%3A6969"],"infoHash":"06d5dd4fd66429a09da7cd59877ea47eb3f4a073","infoHashBuffer":{"type":"Buffer","data":[6,213,221,79,214,100,41,160,157,167,205,89,135,126,164,126,179,244,160,115]},"announce":[],"urlList":[]}}