{"title":"[18XGirls] Laura (Laura Gets A Surprising Massage / 29/10/2012)","uid":7770053,"size":381585971,"categoryP":"porn","categoryS":"movies","magnet":"?xt=urn:btih:0a04e26d437dd32a2c6dd2564470877a2655f14d&amp;dn=%5B18XGirls%5D+Laura+%28Laura+Gets+A+Surprising+Massage+%2F+29%2F10%2F2012%29&amp;tr=udp%3A%2F%2Ftracker.openbittorrent.com%3A80&amp;tr=udp%3A%2F%2Fopen.demonii.com%3A1337&amp;tr=udp%3A%2F%2Ftracker.coppersurfer.tk%3A6969&amp;tr=udp%3A%2F%2Fexodus.desync.com%3A6969","seeders":2,"leechers":0,"uploader":"chkm8te","files":1,"time":1351494559,"description":"[18XGirls] Laura (Laura Gets A Surprising Massage / 29/10/2012)\n\nLaura was in Complete surprise When she Showed up to her Massage session, not Knowing she'd have an Attractive masseuse That'd be Interested in her. After she laid out on the massage table and her guy had the opportunity to feel up her perfect boobs, she knew just what she wanted\n\nScreens: &lt;a href=&quot;\nhttp://xxxhost.me/viewer.php?file=hzidphcntt8g7nnj9yt3.jpg&quot; rel=&quot;nofollow&quot; target=&quot;_NEW&quot;&gt;\nhttp://xxxhost.me/viewer.php?file=hzidphcntt8g7nnj9yt3.jpg&lt;/a&gt;\n &lt;a href=&quot;\nhttp://xxxhost.me/viewer.php?file=p87sc3vez9cfzosjisn5.jpg&quot; rel=&quot;nofollow&quot; target=&quot;_NEW&quot;&gt;\nhttp://xxxhost.me/viewer.php?file=p87sc3vez9cfzosjisn5.jpg&lt;/a&gt;","torrent":{"xt":"urn:btih:0a04e26d437dd32a2c6dd2564470877a2655f14d","amp;dn":"%5B18XGirls%5D+Laura+%28Laura+Gets+A+Surprising+Massage+%2F+29%2F10%2F2012%29","amp;tr":["udp%3A%2F%2Ftracker.openbittorrent.com%3A80","udp%3A%2F%2Fopen.demonii.com%3A1337","udp%3A%2F%2Ftracker.coppersurfer.tk%3A6969","udp%3A%2F%2Fexodus.desync.com%3A6969"],"infoHash":"0a04e26d437dd32a2c6dd2564470877a2655f14d","infoHashBuffer":{"type":"Buffer","data":[10,4,226,109,67,125,211,42,44,109,210,86,68,112,135,122,38,85,241,77]},"announce":[],"urlList":[]}}