{"title":"[TeensLoveHugeCocks] Noelle Easton (Naughty noelle / 07.13.2013)","uid":8681157,"size":348448694,"categoryP":"porn","categoryS":"movies","magnet":"?xt=urn:btih:0db903c47f3ca7bdcff452e6c8e15ee6858595df&amp;dn=%5BTeensLoveHugeCocks%5D+Noelle+Easton+%28Naughty+noelle+%2F+07.13.2013%29&amp;tr=udp%3A%2F%2Ftracker.openbittorrent.com%3A80&amp;tr=udp%3A%2F%2Fopen.demonii.com%3A1337&amp;tr=udp%3A%2F%2Ftracker.coppersurfer.tk%3A6969&amp;tr=udp%3A%2F%2Fexodus.desync.com%3A6969","seeders":2,"leechers":6,"uploader":"chkm8te","files":1,"time":1373703498,"description":"[TeensLoveHugeCocks] Noelle Easton (Naughty noelle / 07.13.2013)\n\nNoelle became totally entranced with her math tutor as soon as she saw him. Her parents expressed some reservations about him but he proved to be a great instructor. Little did they know he was going to instruct their little angel in sexual matters as well. Noelle easily seduced him while he was trying to reinforce what she already should've learned in math class. When a horny little minx like Noelle starts coming on to you there aren't many men who could resist. Especially when the alternative is behaving yourself and conversing about Pi. He was much more interested in her hair pie although she freshly shaved it in anticipation of the seduction. For them, 1+1= fun and cum.\n\nScreens: &lt;a href=&quot;\nhttp://xxxhost.me/viewer.php?file=hzajbudcndpb1wqdwr5a.jpg&quot; rel=&quot;nofollow&quot; target=&quot;_NEW&quot;&gt;\nhttp://xxxhost.me/viewer.php?file=hzajbudcndpb1wqdwr5a.jpg&lt;/a&gt;\n &lt;a href=&quot;\nhttp://xxxhost.me/viewer.php?file=3i6kyqybw6fgfj6j3w82.jpg&quot; rel=&quot;nofollow&quot; target=&quot;_NEW&quot;&gt;\nhttp://xxxhost.me/viewer.php?file=3i6kyqybw6fgfj6j3w82.jpg&lt;/a&gt;","torrent":{"xt":"urn:btih:0db903c47f3ca7bdcff452e6c8e15ee6858595df","amp;dn":"%5BTeensLoveHugeCocks%5D+Noelle+Easton+%28Naughty+noelle+%2F+07.13.2013%29","amp;tr":["udp%3A%2F%2Ftracker.openbittorrent.com%3A80","udp%3A%2F%2Fopen.demonii.com%3A1337","udp%3A%2F%2Ftracker.coppersurfer.tk%3A6969","udp%3A%2F%2Fexodus.desync.com%3A6969"],"infoHash":"0db903c47f3ca7bdcff452e6c8e15ee6858595df","infoHashBuffer":{"type":"Buffer","data":[13,185,3,196,127,60,167,189,207,244,82,230,200,225,94,230,133,133,149,223]},"announce":[],"urlList":[]}}