{"title":"Family Guy Full 5 seasons + Movie","uid":3465680,"size":12433270687,"categoryP":"video","categoryS":"tv_shows","magnet":"?xt=urn:btih:13aedc7a77fb95d4de224e3de44d91d7d3bbff6e&amp;dn=Family+Guy+Full+5+seasons+%2B+Movie&amp;tr=udp%3A%2F%2Ftracker.openbittorrent.com%3A80&amp;tr=udp%3A%2F%2Fopen.demonii.com%3A1337&amp;tr=udp%3A%2F%2Ftracker.coppersurfer.tk%3A6969&amp;tr=udp%3A%2F%2Fexodus.desync.com%3A6969","seeders":2,"leechers":0,"uploader":"SeBoYa","files":-1,"time":1144017941,"description":"Family Guy Full\n5 seasons full, English + spanish subtitles\nStewie Griffin The untold Story DVDRIP English + spanish subtitles","torrent":{"xt":"urn:btih:13aedc7a77fb95d4de224e3de44d91d7d3bbff6e","amp;dn":"Family+Guy+Full+5+seasons+%2B+Movie","amp;tr":["udp%3A%2F%2Ftracker.openbittorrent.com%3A80","udp%3A%2F%2Fopen.demonii.com%3A1337","udp%3A%2F%2Ftracker.coppersurfer.tk%3A6969","udp%3A%2F%2Fexodus.desync.com%3A6969"],"infoHash":"13aedc7a77fb95d4de224e3de44d91d7d3bbff6e","infoHashBuffer":{"type":"Buffer","data":[19,174,220,122,119,251,149,212,222,34,78,61,228,77,145,215,211,187,255,110]},"announce":[],"urlList":[]}}