{"title":"Dangerous_-_Kardinal_Offishall_Ft._Akon_[Sbyky]","uid":7064268,"size":104535168,"categoryP":"video","categoryS":"music_videos","magnet":"?xt=urn:btih:14543eae594a2f6640144b96508cafea0a419608&amp;dn=Dangerous_-_Kardinal_Offishall_Ft._Akon_%5BSbyky%5D&amp;tr=udp%3A%2F%2Ftracker.openbittorrent.com%3A80&amp;tr=udp%3A%2F%2Fopen.demonii.com%3A1337&amp;tr=udp%3A%2F%2Ftracker.coppersurfer.tk%3A6969&amp;tr=udp%3A%2F%2Fexodus.desync.com%3A6969","seeders":2,"leechers":0,"uploader":"Sbyky","files":-1,"time":1330459621,"description":"&quot;Dangerous&quot; is a hip-hop/R&amp;B song by Kardinal Offishall featuring Akon. Produced by DJ Kemo \n\nand hAZEL,[2] it was the first single from his fourth album Not 4 Sale. It was released to \n\nradio in March 2008, and on iTunes on April 1. On the week of May 13, at the American \n\niTunes store, the song was offered as a free download (Single of the Week). The song won \n\nthe award for Single of the Year at the 2009 Juno Awards.[3] In March 2010, the single was \n\ncertified 3x Platinum by the CRIA.[1]\n\n\n\n\n\n\nThe music video was shot in Miami, Florida and directed by Gil Green. It debuted in early \n\nMay on AOL.com. It starts off with a girl (Chanta Patton) passing by Kardinal, Akon, and \n\nfriends as all of them watch her and follow her. Most of the scenes start by zooming out of \n\nobjects such as sunglasses, a drinking cup, etc. It has scenes in a restaurant, a club, and \n\na beach. There are cameo appearances in the video by DJ Khaled, Red Cafe, Black Chiney, \n\nClinton Sparks, and many more.","torrent":{"xt":"urn:btih:14543eae594a2f6640144b96508cafea0a419608","amp;dn":"Dangerous_-_Kardinal_Offishall_Ft._Akon_%5BSbyky%5D","amp;tr":["udp%3A%2F%2Ftracker.openbittorrent.com%3A80","udp%3A%2F%2Fopen.demonii.com%3A1337","udp%3A%2F%2Ftracker.coppersurfer.tk%3A6969","udp%3A%2F%2Fexodus.desync.com%3A6969"],"infoHash":"14543eae594a2f6640144b96508cafea0a419608","infoHashBuffer":{"type":"Buffer","data":[20,84,62,174,89,74,47,102,64,20,75,150,80,140,175,234,10,65,150,8]},"announce":[],"urlList":[]}}