{"title":"Portlandia.S03E02.720p.HDTV.x264-EVOLVE","uid":7988921,"size":718666015,"categoryP":"video","categoryS":"hd___tv_shows","magnet":"?xt=urn:btih:1bb79d3b8e566eee558881b9924bcee63eb2c42b&amp;dn=Portlandia.S03E02.720p.HDTV.x264-EVOLVE&amp;tr=udp%3A%2F%2Ftracker.openbittorrent.com%3A80&amp;tr=udp%3A%2F%2Fopen.demonii.com%3A1337&amp;tr=udp%3A%2F%2Ftracker.coppersurfer.tk%3A6969&amp;tr=udp%3A%2F%2Fexodus.desync.com%3A6969","seeders":2,"leechers":0,"uploader":"sceneline","files":19,"time":1357361054,"description":"- &lt;a href=&quot;\nhttp://www.Speed.Cd&quot; rel=&quot;nofollow&quot; target=&quot;_NEW&quot;&gt;\nhttp://www.Speed.Cd&lt;/a&gt;\n &lt;a href=&quot;\nhttp://www.Speed.Cd&quot; rel=&quot;nofollow&quot; target=&quot;_NEW&quot;&gt;\nhttp://www.Speed.Cd&lt;/a&gt;       the fast  and The Hottest Private Tracker on the net\n\nPlease Seed back to make the speed Faster!!\n ............ NFO .............\n-Portlandia.S03E02.720p.HDTV.x264-EVOLVE\n\nDate: Sat 01/05/2013\nSize: 685 MiB\nRuntime: 22mn 32s\nFrameRate: 23.976\nBitRate: 3 782 Kbps\nResolution: 1280 x 720\nAudio: 6 ch\nCRF: 19\nPreset: Slow","torrent":{"xt":"urn:btih:1bb79d3b8e566eee558881b9924bcee63eb2c42b","amp;dn":"Portlandia.S03E02.720p.HDTV.x264-EVOLVE","amp;tr":["udp%3A%2F%2Ftracker.openbittorrent.com%3A80","udp%3A%2F%2Fopen.demonii.com%3A1337","udp%3A%2F%2Ftracker.coppersurfer.tk%3A6969","udp%3A%2F%2Fexodus.desync.com%3A6969"],"infoHash":"1bb79d3b8e566eee558881b9924bcee63eb2c42b","infoHashBuffer":{"type":"Buffer","data":[27,183,157,59,142,86,110,238,85,136,129,185,146,75,206,230,62,178,196,43]},"announce":[],"urlList":[]}}