{"title":"The Definitive Dean Koontz Collection of Audiobooks","uid":7002323,"size":23161084437,"categoryP":"audio","categoryS":"audio_books","magnet":"?xt=urn:btih:29b69674a76cfed1924665847b9051c4af1c8ba8&amp;dn=The+Definitive+Dean+Koontz+Collection+of+Audiobooks&amp;tr=udp%3A%2F%2Ftracker.openbittorrent.com%3A80&amp;tr=udp%3A%2F%2Fopen.demonii.com%3A1337&amp;tr=udp%3A%2F%2Ftracker.coppersurfer.tk%3A6969&amp;tr=udp%3A%2F%2Fexodus.desync.com%3A6969","seeders":2,"leechers":3,"uploader":"smartskallen","files":2414,"time":1328106156,"description":"Ebooks, short stories, books, a radio interview. ALL of it!\n\n1972 - Dean Koontz - Chase\n1973 - Dean Koontz - Demon Seed\n1973 - Dean Koontz - Shattered\n1974 - Dean Koontz - After the Last Race\n1975 - Dean Koontz - Invasion\n1975 - Dean Koontz - Nightmare Journey\n1976 - Dean Koontz - Night Chills\n1977 - Dean Koontz - The Vision\n1979 - Dean Koontz - The Key to Midnight\n1980 - Dean Koontz - The Funhouse\n1980 - Dean Koontz - The Voice Of The Night\n1981 - Dean Koontz - Eyes of Darkness\n1981 - Dean Koontz - The Mask (Unabridged)\n1982 - Dean Koontz - House of Thunder\n1983 - Dean Koontz - Phantoms\n1984 - Dean Koontz - Darkfall (Unabridged)\n1984 - Dean Koontz - The Servants of Twilight\n1985 - Dean Koontz - The Door to December\n1985 - Dean Koontz - Twilight Eyes (Unabridged)\n1986 - Dean Koontz - Down In The Darkness\n1986 - Dean Koontz - Strangers\n1987 - Dean Koontz - Shadowfires (Unabridged)\n1987 - Dean Koontz - Watchers\n1988 - Dean Koontz - Lightning\n1989 - Dean Koontz - Midnight\n1990 - Dean Koontz - The Bad Place\n1992 - Dean Koontz - Hideaway\n1993 - Dean Koontz - Dragon Tears\n1993 - Dean Koontz - Mr. Murder\n1993 - Dean Koontz - Trapped\n1994 - Dean Koontz - Dark Rivers Of The Heart\n1994 - Dean Koontz - Winter Moon (by tucky man)\n1995 - Dean Koontz - Icebound\n1995 - Dean Koontz - Intensity\n1995 - Dean Koontz - Strange Highways\n1996 - Dean Koontz - Santa's Twin\n1996 - Dean Koontz - Tick Tock\n1997 - Dean Koontz - Sole Survivor\n1998 - Dean Koontz - Fear Nothing (Moonlight bay)\n1999 - Dean Koontz - Black River\n1999 - Dean Koontz - False Memory\n2000 - Dean Koontz - From the Corner of His Eye\n2001 - Dean Koontz - One Door Away From Heaven\n2002 - Dean Koontz - By the Light Of the Moon\n2003 - Dean Koontz - The Face\n2004 - Dean Koontz - Cold Fire\n2004 - Dean Koontz - Life Expectancy\n2004 - Dean Koontz - The Taking\n2005 - Dean Koontz - Velocity\n2006 - Dean Koontz - The Husband\n2007 - Dean Koontz - The Darkest Evening Of The Year\n2007 - Dean Koontz - The good guy\n2008 - Dean Koontz - Bliss To You - Trixie's Guide to a Happy Life\n2008 - Dean Koontz - Your Heart Belongs To Me\n2009 - Dean Koontz - Breathless (Unabridged)\n2009 - Dean Koontz - Relentless\n2011 - Dean Koontz - 77 Shadow Street\nDean Koontz - Radio interview 01-22-2002\nDean Koontz - The Frankenstein books (four of them)\nDean Koontz - The Odd Thomas Books (Odd Thomas, Forever Odd, Brother Odd)\nEbooks\n\nEnjoy, my friends!","torrent":{"xt":"urn:btih:29b69674a76cfed1924665847b9051c4af1c8ba8","amp;dn":"The+Definitive+Dean+Koontz+Collection+of+Audiobooks","amp;tr":["udp%3A%2F%2Ftracker.openbittorrent.com%3A80","udp%3A%2F%2Fopen.demonii.com%3A1337","udp%3A%2F%2Ftracker.coppersurfer.tk%3A6969","udp%3A%2F%2Fexodus.desync.com%3A6969"],"infoHash":"29b69674a76cfed1924665847b9051c4af1c8ba8","infoHashBuffer":{"type":"Buffer","data":[41,182,150,116,167,108,254,209,146,70,101,132,123,144,81,196,175,28,139,168]},"announce":[],"urlList":[]}}