{"title":"18YearsOld - No One Is Home - Whitney Westgate.mp4","uid":7523764,"size":474364402,"categoryP":"porn","categoryS":"movie_clips","magnet":"?xt=urn:btih:2d6f6ffb30a3a668bc2c927d7a96af332c83f2f2&amp;dn=18YearsOld+-+No+One+Is+Home+-+Whitney+Westgate.mp4&amp;tr=udp%3A%2F%2Ftracker.openbittorrent.com%3A80&amp;tr=udp%3A%2F%2Fopen.demonii.com%3A1337&amp;tr=udp%3A%2F%2Ftracker.coppersurfer.tk%3A6969&amp;tr=udp%3A%2F%2Fexodus.desync.com%3A6969","seeders":2,"leechers":1,"uploader":"1.No.1","files":-1,"time":1344715090,"description":"18YearsOld - No One Is Home - Whitney Westgate.mp4\n\n2012, Blowjob, Teen, Amateur, Brunettes, Hardcore, XXX, Adult\n\n950 x 534\n\n00:24:20\n\n452.39 MB\n\nScreens\n &lt;a href=&quot;\nhttp://www.pixsor.com/share-A3A4_50269E9E.html&quot; rel=&quot;nofollow&quot; target=&quot;_NEW&quot;&gt;\nhttp://www.pixsor.com/share-A3A4_50269E9E.html&lt;/a&gt;\n &lt;a href=&quot;\nhttp://www.pixsor.com/share-0478_50269E9E.html&quot; rel=&quot;nofollow&quot; target=&quot;_NEW&quot;&gt;\nhttp://www.pixsor.com/share-0478_50269E9E.html&lt;/a&gt;","torrent":{"xt":"urn:btih:2d6f6ffb30a3a668bc2c927d7a96af332c83f2f2","amp;dn":"18YearsOld+-+No+One+Is+Home+-+Whitney+Westgate.mp4","amp;tr":["udp%3A%2F%2Ftracker.openbittorrent.com%3A80","udp%3A%2F%2Fopen.demonii.com%3A1337","udp%3A%2F%2Ftracker.coppersurfer.tk%3A6969","udp%3A%2F%2Fexodus.desync.com%3A6969"],"infoHash":"2d6f6ffb30a3a668bc2c927d7a96af332c83f2f2","infoHashBuffer":{"type":"Buffer","data":[45,111,111,251,48,163,166,104,188,44,146,125,122,150,175,51,44,131,242,242]},"announce":[],"urlList":[]}}