{"title":"Deranged (1974).DVDRip.XviD.MultiSub","uid":6428348,"size":743301214,"categoryP":"video","categoryS":"movies","magnet":"?xt=urn:btih:301ec19c79e9fe2afd32c7021da38c505aff31ca&amp;dn=Deranged+%281974%29.DVDRip.XviD.MultiSub&amp;tr=udp%3A%2F%2Ftracker.openbittorrent.com%3A80&amp;tr=udp%3A%2F%2Fopen.demonii.com%3A1337&amp;tr=udp%3A%2F%2Ftracker.coppersurfer.tk%3A6969&amp;tr=udp%3A%2F%2Fexodus.desync.com%3A6969","seeders":2,"leechers":1,"uploader":"Arrrrrrrrrr","files":-1,"time":1306559572,"description":"Deranged | 1974 | Canada/USA\n\nGenre:    Crime | Horror | Docudrama\nRuntime:  1:48:42\nSource:   DVD\nEncoding: XviD\nVideo:    624x336, 23.97 fps, 16:9 aspect ratio\nAudio:    MPEG Stereo, 48kHz, 128kbps\nLanguage: English(audio), English/French/Spanish (subtitles)\nIMDB:    &lt;a href=&quot; http://www.imdb.com/title/tt0071408/&quot; rel=&quot;nofollow&quot; target=&quot;_NEW&quot;&gt; http://www.imdb.com/title/tt0071408/&lt;/a&gt;\nRating:   6.6/10 (1,567 votes)\n\nSummary: Based on the Ed Gein case, a deranged rural farmer becomes a grave robber and murderer after the death of his possessive mother.\nStarring: Roberts Blossom, Cosette Lee and Leslie Carlson\nDirected by: Jeff Gillen and Alan Ormsby\n\nNotes:\n\n - This is a reseed/mirror; not my encode. Another version is posted here ( http://thepiratebay.se/torrent/4118973/Deranged.DvDrip.1974.KayzerZoze ) but this torrent has been dead for months.\n \n - Please make sure to seed as much as you download and do your part so that free media will always be available. If everyone seeded to at least 101%, no torrent would ever die.","torrent":{"xt":"urn:btih:301ec19c79e9fe2afd32c7021da38c505aff31ca","amp;dn":"Deranged+%281974%29.DVDRip.XviD.MultiSub","amp;tr":["udp%3A%2F%2Ftracker.openbittorrent.com%3A80","udp%3A%2F%2Fopen.demonii.com%3A1337","udp%3A%2F%2Ftracker.coppersurfer.tk%3A6969","udp%3A%2F%2Fexodus.desync.com%3A6969"],"infoHash":"301ec19c79e9fe2afd32c7021da38c505aff31ca","infoHashBuffer":{"type":"Buffer","data":[48,30,193,156,121,233,254,42,253,50,199,2,29,163,140,80,90,255,49,202]},"announce":[],"urlList":[]}}