{"title":"Rock.Band.The.Beatles.RF-XBOX360","uid":5119949,"size":7840846166,"categoryP":"games","categoryS":"xbox360","magnet":"?xt=urn:btih:372961bf72491f3750e35be36fb24225126b4040&amp;dn=Rock.Band.The.Beatles.RF-XBOX360&amp;tr=udp%3A%2F%2Ftracker.openbittorrent.com%3A80&amp;tr=udp%3A%2F%2Fopen.demonii.com%3A1337&amp;tr=udp%3A%2F%2Ftracker.coppersurfer.tk%3A6969&amp;tr=udp%3A%2F%2Fexodus.desync.com%3A6969","seeders":2,"leechers":0,"uploader":"styvabananen","files":-1,"time":1255278025,"description":"VÃƒÂ¤rldens ledande musikspel mÃƒÂ¶ter musikhistoriens stÃƒÂ¶rsta band! The BeatlesT: Rock BandT ger fansen vad de vÃƒÂ¤ntat pÃƒÂ¥: en chans att uppleva musiklegenderna Beatles frÃƒÂ¥n insidan. Du kommer inte bara fÃƒÂ¥ mÃƒÂ¶jligheten att se och lyssna nÃƒÂ¤r The Beatles skapade rockhistoria, klassiska album och erÃƒÂ¶vrade vÃƒÂ¤rlden...du kommer dessutom att vara en del av bandet. The BeatlesT-mjukvaran ÃƒÂ¤r kompatibel med Rock BandT, Guitar Hero och de flesta andra instrumentkontroller sÃƒÂ¥ vÃƒÂ¤l sommikrofoner frÃƒÂ¥n tredje part som exempelvis SingStar och Lips.\n\n\nLanguage:....English","torrent":{"xt":"urn:btih:372961bf72491f3750e35be36fb24225126b4040","amp;dn":"Rock.Band.The.Beatles.RF-XBOX360","amp;tr":["udp%3A%2F%2Ftracker.openbittorrent.com%3A80","udp%3A%2F%2Fopen.demonii.com%3A1337","udp%3A%2F%2Ftracker.coppersurfer.tk%3A6969","udp%3A%2F%2Fexodus.desync.com%3A6969"],"infoHash":"372961bf72491f3750e35be36fb24225126b4040","infoHashBuffer":{"type":"Buffer","data":[55,41,97,191,114,73,31,55,80,227,91,227,111,178,66,37,18,107,64,64]},"announce":[],"urlList":[]}}