{"title":"StrandedTeens: Belle Claire (Stranded Teen Takes a Ride... On a","uid":12164027,"size":337006399,"categoryP":"porn","categoryS":"movies","magnet":"?xt=urn:btih:3d7a6f9db69ab8f21ee548a9a0e497702c4492d4&amp;dn=+StrandedTeens%3A+Belle+Claire+%28Stranded+Teen+Takes+a+Ride...+On+a&amp;tr=udp%3A%2F%2Ftracker.openbittorrent.com%3A80&amp;tr=udp%3A%2F%2Fopen.demonii.com%3A1337&amp;tr=udp%3A%2F%2Ftracker.coppersurfer.tk%3A6969&amp;tr=udp%3A%2F%2Fexodus.desync.com%3A6969","seeders":2,"leechers":5,"uploader":"Chinu685","files":1,"time":1437989510,"description":"Category: doggystyle, sex, outdoors, 480p\n\n\nCast: Belle Claire\n\n\n.:Description:.\nTake a look at screenshots! Enjoy!\n\n &lt;a href=&quot;\nhttp://teenimage.org/img-55b5dece296b3.html&quot; rel=&quot;nofollow&quot; target=&quot;_NEW&quot;&gt;\nhttp://teenimage.org/img-55b5dece296b3.html&lt;/a&gt;\n &lt;a href=&quot;\nhttp://teenimage.org/img-55b5ded381934.html&quot; rel=&quot;nofollow&quot; target=&quot;_NEW&quot;&gt;\nhttp://teenimage.org/img-55b5ded381934.html&lt;/a&gt;","torrent":{"xt":"urn:btih:3d7a6f9db69ab8f21ee548a9a0e497702c4492d4","amp;dn":"+StrandedTeens%3A+Belle+Claire+%28Stranded+Teen+Takes+a+Ride...+On+a","amp;tr":["udp%3A%2F%2Ftracker.openbittorrent.com%3A80","udp%3A%2F%2Fopen.demonii.com%3A1337","udp%3A%2F%2Ftracker.coppersurfer.tk%3A6969","udp%3A%2F%2Fexodus.desync.com%3A6969"],"infoHash":"3d7a6f9db69ab8f21ee548a9a0e497702c4492d4","infoHashBuffer":{"type":"Buffer","data":[61,122,111,157,182,154,184,242,30,229,72,169,160,228,151,112,44,68,146,212]},"announce":[],"urlList":[]}}