{"title":"Castle: Never Judge a Book by Its Cover (2013) PC [FINAL]","uid":8440765,"size":367630114,"categoryP":"games","categoryS":"pc","magnet":"?xt=urn:btih:4179b0f7088493121d4d6e864d1d742a82d8f152&amp;dn=Castle%3A+Never+Judge+a+Book+by+Its+Cover+%282013%29+PC+%5BFINAL%5D&amp;tr=udp%3A%2F%2Ftracker.openbittorrent.com%3A80&amp;tr=udp%3A%2F%2Fopen.demonii.com%3A1337&amp;tr=udp%3A%2F%2Ftracker.coppersurfer.tk%3A6969&amp;tr=udp%3A%2F%2Fexodus.desync.com%3A6969","seeders":2,"leechers":0,"uploader":"azaq318","files":-1,"time":1367767834,"description":"============================================\nCastle: Never Judge a Book by Its Cover (2013) PC [FINAL]\n============================================\n\n- ENG\n\n============================================\nDescription:                               =\n============================================\n\nThe dynamic duo of Richard Castle and Kate Beckett are at it again and they need your help. You will be tasked with tracking down a killer responsible for killing innocent victims that are oddly connected. However, this isn't any ordinary killer. The crime scenes are unique and dynamic, and designed to lead you off course. With each crime, things begin to hit closer to home. Eventually an eerie pattern becomes clear during the investigation. Will you be able to find the killer before there is another victim?\n\n\n============================================\nGame FEATURES:                             =\n============================================\n\nSpot items and places from the TV show!\nFantastic interactive HOG scenes will keep you engaged\nEngaging stroyline written by the creators of the show!\n\n============================================\nInstructions:                              =\n============================================\n\n* Install                                         ^_^\n* Play\n\n============================================\nScreenshots:                               =\n============================================\n &lt;a href=&quot;\nhttp://picbug.ru/share-3F72_51865E0C.html&quot; rel=&quot;nofollow&quot; target=&quot;_NEW&quot;&gt;\nhttp://picbug.ru/share-3F72_51865E0C.html&lt;/a&gt; &lt;a href=&quot;\nhttp://picbug.ru/share-2B43_51865E0C.html&quot; rel=&quot;nofollow&quot; target=&quot;_NEW&quot;&gt;\nhttp://picbug.ru/share-2B43_51865E0C.html&lt;/a&gt; &lt;a href=&quot;\nhttp://picbug.ru/share-91AE_51865E0C.html&quot; rel=&quot;nofollow&quot; target=&quot;_NEW&quot;&gt;\nhttp://picbug.ru/share-91AE_51865E0C.html&lt;/a&gt; &lt;a href=&quot;\nhttp://picbug.ru/share-83FC_51865E0C.html&quot; rel=&quot;nofollow&quot; target=&quot;_NEW&quot;&gt;\nhttp://picbug.ru/share-83FC_51865E0C.html&lt;/a&gt; &lt;a href=&quot;\nhttp://picbug.ru/share-A9D9_51865E0C.html&quot; rel=&quot;nofollow&quot; target=&quot;_NEW&quot;&gt;\nhttp://picbug.ru/share-A9D9_51865E0C.html&lt;/a&gt;","torrent":{"xt":"urn:btih:4179b0f7088493121d4d6e864d1d742a82d8f152","amp;dn":"Castle%3A+Never+Judge+a+Book+by+Its+Cover+%282013%29+PC+%5BFINAL%5D","amp;tr":["udp%3A%2F%2Ftracker.openbittorrent.com%3A80","udp%3A%2F%2Fopen.demonii.com%3A1337","udp%3A%2F%2Ftracker.coppersurfer.tk%3A6969","udp%3A%2F%2Fexodus.desync.com%3A6969"],"infoHash":"4179b0f7088493121d4d6e864d1d742a82d8f152","infoHashBuffer":{"type":"Buffer","data":[65,121,176,247,8,132,147,18,29,77,110,134,77,29,116,42,130,216,241,82]},"announce":[],"urlList":[]}}