{"title":"NGINX High Performance","uid":12667340,"size":9118852,"categoryP":"other","categoryS":"e_books","magnet":"?xt=urn:btih:6158e2d3649a870b84a506e2ee91d25978841a78&amp;dn=NGINX+High+Performance&amp;tr=udp%3A%2F%2Ftracker.leechers-paradise.org%3A6969&amp;tr=udp%3A%2F%2Fzer0day.ch%3A1337&amp;tr=udp%3A%2F%2Fopen.demonii.com%3A1337&amp;tr=udp%3A%2F%2Ftracker.coppersurfer.tk%3A6969&amp;tr=udp%3A%2F%2Fexodus.desync.com%3A6969","seeders":2,"leechers":0,"uploader":"Argish","files":1,"time":1446380525,"description":"Optimize NGINX for high-performance, scalable web applications\r\n\r\n\r\n** PLEASE IF YOU LIKE THIS EBOOK BUY IT AND SUPPORT THE AUTHOR **","torrent":{"xt":"urn:btih:6158e2d3649a870b84a506e2ee91d25978841a78","amp;dn":"NGINX+High+Performance","amp;tr":["udp%3A%2F%2Ftracker.leechers-paradise.org%3A6969","udp%3A%2F%2Fzer0day.ch%3A1337","udp%3A%2F%2Fopen.demonii.com%3A1337","udp%3A%2F%2Ftracker.coppersurfer.tk%3A6969","udp%3A%2F%2Fexodus.desync.com%3A6969"],"infoHash":"6158e2d3649a870b84a506e2ee91d25978841a78","infoHashBuffer":{"type":"Buffer","data":[97,88,226,211,100,154,135,11,132,165,6,226,238,145,210,89,120,132,26,120]},"announce":[],"urlList":[]}}