{"title":"The Secret Life of the American Teenager S05E13 HDTV x264-ASAP[e","uid":8273584,"size":294502408,"categoryP":"video","categoryS":"tv_shows","magnet":"?xt=urn:btih:719d275b03f0f39626f2acc6d58e9010a481e7e9&amp;dn=The+Secret+Life+of+the+American+Teenager+S05E13+HDTV+x264-ASAP%5Be&amp;tr=udp%3A%2F%2Ftracker.openbittorrent.com%3A80&amp;tr=udp%3A%2F%2Fopen.demonii.com%3A1337&amp;tr=udp%3A%2F%2Ftracker.coppersurfer.tk%3A6969&amp;tr=udp%3A%2F%2Fexodus.desync.com%3A6969","seeders":2,"leechers":0,"uploader":"ettv","files":2,"time":1363658931,"description":"x264\nEncode Information\nResolution....: 720x402\nVideo : x264\nAudio : AAC 2ch 48khz\nFrame Rate : 23.976024 fps &lt;a href=&quot;\nhttp://www.imdb.com/&quot; rel=&quot;nofollow&quot; target=&quot;_NEW&quot;&gt;\nhttp://www.imdb.com/&lt;/a&gt;\n","torrent":{"xt":"urn:btih:719d275b03f0f39626f2acc6d58e9010a481e7e9","amp;dn":"The+Secret+Life+of+the+American+Teenager+S05E13+HDTV+x264-ASAP%5Be","amp;tr":["udp%3A%2F%2Ftracker.openbittorrent.com%3A80","udp%3A%2F%2Fopen.demonii.com%3A1337","udp%3A%2F%2Ftracker.coppersurfer.tk%3A6969","udp%3A%2F%2Fexodus.desync.com%3A6969"],"infoHash":"719d275b03f0f39626f2acc6d58e9010a481e7e9","infoHashBuffer":{"type":"Buffer","data":[113,157,39,91,3,240,243,150,38,242,172,198,213,142,144,16,164,129,231,233]},"announce":[],"urlList":[]}}