{"title":"[EroticaX] Marina Visconti (True Blue / 08.01.2014)","uid":10671303,"size":1408845877,"categoryP":"porn","categoryS":"hd___movies","magnet":"?xt=urn:btih:724a7636e2f4703bf45b26ba036130bdd6b6157f&amp;dn=%5BEroticaX%5D+Marina+Visconti+%28True+Blue+%2F+08.01.2014%29&amp;tr=udp%3A%2F%2Ftracker.openbittorrent.com%3A80&amp;tr=udp%3A%2F%2Fopen.demonii.com%3A1337&amp;tr=udp%3A%2F%2Ftracker.coppersurfer.tk%3A6969&amp;tr=udp%3A%2F%2Fexodus.desync.com%3A6969","seeders":2,"leechers":0,"uploader":"chkm8te","files":1,"time":1406875133,"description":"[EroticaX] Marina Visconti (True Blue / 08.01.2014)\nres:1080p\n\nRacked Russian and all-natural brunette Marina Visconti stars along side Danny Mountain in this very sensuous edition of EroticaX. Their presence in front of the camera is undeniably alluring and new-comer Marina will not leave you wanting. Her perfect 34DD breasts are blindingly beautiful and we envy Danny for having had the chance to bury himself in them.\n\nScreens: &lt;a href=&quot;\nhttp://xxxhost.me/viewer.php?file=es317jc3l0o78n0jgjya.jpg&quot; rel=&quot;nofollow&quot; target=&quot;_NEW&quot;&gt;\nhttp://xxxhost.me/viewer.php?file=es317jc3l0o78n0jgjya.jpg&lt;/a&gt;\n &lt;a href=&quot;\nhttp://xxxhost.me/viewer.php?file=9jvggyzec8luqyssgcmx.jpg&quot; rel=&quot;nofollow&quot; target=&quot;_NEW&quot;&gt;\nhttp://xxxhost.me/viewer.php?file=9jvggyzec8luqyssgcmx.jpg&lt;/a&gt;","torrent":{"xt":"urn:btih:724a7636e2f4703bf45b26ba036130bdd6b6157f","amp;dn":"%5BEroticaX%5D+Marina+Visconti+%28True+Blue+%2F+08.01.2014%29","amp;tr":["udp%3A%2F%2Ftracker.openbittorrent.com%3A80","udp%3A%2F%2Fopen.demonii.com%3A1337","udp%3A%2F%2Ftracker.coppersurfer.tk%3A6969","udp%3A%2F%2Fexodus.desync.com%3A6969"],"infoHash":"724a7636e2f4703bf45b26ba036130bdd6b6157f","infoHashBuffer":{"type":"Buffer","data":[114,74,118,54,226,244,112,59,244,91,38,186,3,97,48,189,214,182,21,127]},"announce":[],"urlList":[]}}