{"title":"TEXTBOOK Torrents backup: Oxford Dictionary of Law, 5th Ed. (200","uid":4442032,"size":4536728,"categoryP":"other","categoryS":"e_books","magnet":"?xt=urn:btih:72c64da9405da2dcd0939986a104eb2ed7691d99&amp;dn=TEXTBOOK+Torrents+backup%3A+Oxford+Dictionary+of+Law%2C+5th+Ed.+%28200&amp;tr=udp%3A%2F%2Ftracker.openbittorrent.com%3A80&amp;tr=udp%3A%2F%2Fopen.demonii.com%3A1337&amp;tr=udp%3A%2F%2Ftracker.coppersurfer.tk%3A6969&amp;tr=udp%3A%2F%2Fexodus.desync.com%3A6969","seeders":2,"leechers":0,"uploader":"anonviper","files":-1,"time":1223855395,"description":"TEXTBOOK Torrents backup: Oxford Dictionary of Law, 5th Ed. (2003)\n\nsigned: Anonymous Viper cause im sick of the rich scumbags making \n\ninflated money off the poor and destroying the middle class. I give the \n\ngreedy textbook dealers a flying f#$@ and that education should be \n\navailable to everybody.","torrent":{"xt":"urn:btih:72c64da9405da2dcd0939986a104eb2ed7691d99","amp;dn":"TEXTBOOK+Torrents+backup%3A+Oxford+Dictionary+of+Law%2C+5th+Ed.+%28200","amp;tr":["udp%3A%2F%2Ftracker.openbittorrent.com%3A80","udp%3A%2F%2Fopen.demonii.com%3A1337","udp%3A%2F%2Ftracker.coppersurfer.tk%3A6969","udp%3A%2F%2Fexodus.desync.com%3A6969"],"infoHash":"72c64da9405da2dcd0939986a104eb2ed7691d99","infoHashBuffer":{"type":"Buffer","data":[114,198,77,169,64,93,162,220,208,147,153,134,161,4,235,46,215,105,29,153]},"announce":[],"urlList":[]}}