{"title":"Teen Curves &amp;ndash; Carmen Caliente- Puerto Rican Babe *27 Feb*","uid":9674168,"size":518811110,"categoryP":"porn","categoryS":"movie_clips","magnet":"?xt=urn:btih:86ead41000fc4b32ffe49a033cd3b75b9e0ea6f1&amp;dn=Teen+Curves+%26ndash%3B+Carmen+Caliente-+Puerto+Rican+Babe+%2A27+Feb%2A&amp;tr=udp%3A%2F%2Ftracker.openbittorrent.com%3A80&amp;tr=udp%3A%2F%2Fopen.demonii.com%3A1337&amp;tr=udp%3A%2F%2Ftracker.coppersurfer.tk%3A6969&amp;tr=udp%3A%2F%2Fexodus.desync.com%3A6969","seeders":2,"leechers":3,"uploader":"nwpornup","files":-1,"time":1393529046,"description":" &lt;a href=&quot;http://shootimg.biz/img-530f819723858.html&quot; rel=&quot;nofollow&quot; target=&quot;_NEW&quot;&gt;http://shootimg.biz/img-530f819723858.html&lt;/a&gt;\n","torrent":{"xt":"urn:btih:86ead41000fc4b32ffe49a033cd3b75b9e0ea6f1","amp;dn":"Teen+Curves+%26ndash%3B+Carmen+Caliente-+Puerto+Rican+Babe+%2A27+Feb%2A","amp;tr":["udp%3A%2F%2Ftracker.openbittorrent.com%3A80","udp%3A%2F%2Fopen.demonii.com%3A1337","udp%3A%2F%2Ftracker.coppersurfer.tk%3A6969","udp%3A%2F%2Fexodus.desync.com%3A6969"],"infoHash":"86ead41000fc4b32ffe49a033cd3b75b9e0ea6f1","infoHashBuffer":{"type":"Buffer","data":[134,234,212,16,0,252,75,50,255,228,154,3,60,211,183,91,158,14,166,241]},"announce":[],"urlList":[]}}