{"title":"Simon And Garfunkel 20 Greatest Hits [320 Kbps]","uid":5486288,"size":182962589,"categoryP":"audio","categoryS":"music","magnet":"?xt=urn:btih:9b955e35a1e904698c38662f406a3741ff4de732&amp;dn=Simon+And+Garfunkel+20+Greatest+Hits+%5B320+Kbps%5D&amp;tr=udp%3A%2F%2Ftracker.openbittorrent.com%3A80&amp;tr=udp%3A%2F%2Fopen.demonii.com%3A1337&amp;tr=udp%3A%2F%2Ftracker.coppersurfer.tk%3A6969&amp;tr=udp%3A%2F%2Fexodus.desync.com%3A6969","seeders":2,"leechers":2,"uploader":"320hunter","files":24,"time":1270738201,"description":"                     Simon And Garfunkel 20 Greatest Hits [320 Kbps]\n\n\n\n\n\n01 The Sound Of Silence                     03:04\n02 Homeward Bound                           02:26\n03 I Am A Rock                              02:50 \n04 America                                  03:27 \n05 The 59th Street Bridge Song              01:41 \n06 Cloudy                                   02:11 \n07 At The Zoo                               02:17 \n08 El Condor Pasa                           03:06 \n09 Hazy Shade Of Winter                     02:17 \n10 We've Got A Groovy Thing Goin'           01:58 \n11 Cecilia                                  02:49 \n12 Keep The Customer Satisfied              02:33 \n13 Mrs Robinson                             03:55 \n14 The Boxer                                05:10 \n15 Scarborough Fair/Canticle                03:07 \n16 The Dangling Conversation                02:37 \n17 Old Friends, Bookends Theme              03:54 \n18 For Emily, Whenever I May Find Her       02:03 \n19 Bridge Over Troubled Water               04:51 \n20 Song For The Asking                      01:42 \n\n\nBitrate: 320 kbps \nChannels: stereo\nSamplerate: 44100\nEncoder: LAME 3.82\nCRC: no\nCopyright: no\nPrivate: no\nOriginal: yes","torrent":{"xt":"urn:btih:9b955e35a1e904698c38662f406a3741ff4de732","amp;dn":"Simon+And+Garfunkel+20+Greatest+Hits+%5B320+Kbps%5D","amp;tr":["udp%3A%2F%2Ftracker.openbittorrent.com%3A80","udp%3A%2F%2Fopen.demonii.com%3A1337","udp%3A%2F%2Ftracker.coppersurfer.tk%3A6969","udp%3A%2F%2Fexodus.desync.com%3A6969"],"infoHash":"9b955e35a1e904698c38662f406a3741ff4de732","infoHashBuffer":{"type":"Buffer","data":[155,149,94,53,161,233,4,105,140,56,102,47,64,106,55,65,255,77,231,50]},"announce":[],"urlList":[]}}