{"title":"Thin Lizzy - Black Rose 1979 (320k) Rock","uid":4979664,"size":93279177,"categoryP":"audio","categoryS":"music","magnet":"?xt=urn:btih:ab9e586256f83d362415a0af766e28454a7ced41&amp;dn=Thin+Lizzy+-+Black+Rose+1979+%28320k%29+Rock&amp;tr=udp%3A%2F%2Ftracker.openbittorrent.com%3A80&amp;tr=udp%3A%2F%2Fopen.demonii.com%3A1337&amp;tr=udp%3A%2F%2Ftracker.coppersurfer.tk%3A6969&amp;tr=udp%3A%2F%2Fexodus.desync.com%3A6969","seeders":2,"leechers":1,"uploader":null,"files":9,"time":1246213079,"description":"Black Rose - 1979\nTrack list and album cover  &lt;a href=&quot;\nhttp://avitochol.org/daba.php?band=Thin+Lizzy&amp;a=Black+Rose&quot; rel=&quot;nofollow&quot; target=&quot;_NEW&quot;&gt;\nhttp://avitochol.org/daba.php?band=Thin+Lizzy&amp;a=Black+Rose&lt;/a&gt;\n\nThin Lizzy discography  &lt;a href=&quot;\nhttp://avitochol.org/dabd.php?d=Thin+Lizzy&quot; rel=&quot;nofollow&quot; target=&quot;_NEW&quot;&gt;\nhttp://avitochol.org/dabd.php?d=Thin+Lizzy&lt;/a&gt;\n\nThin Lizzy biography  &lt;a href=&quot;\nhttp://avitochol.org/dab.php?b=Thin+Lizzy&quot; rel=&quot;nofollow&quot; target=&quot;_NEW&quot;&gt;\nhttp://avitochol.org/dab.php?b=Thin+Lizzy&lt;/a&gt;","torrent":{"xt":"urn:btih:ab9e586256f83d362415a0af766e28454a7ced41","amp;dn":"Thin+Lizzy+-+Black+Rose+1979+%28320k%29+Rock","amp;tr":["udp%3A%2F%2Ftracker.openbittorrent.com%3A80","udp%3A%2F%2Fopen.demonii.com%3A1337","udp%3A%2F%2Ftracker.coppersurfer.tk%3A6969","udp%3A%2F%2Fexodus.desync.com%3A6969"],"infoHash":"ab9e586256f83d362415a0af766e28454a7ced41","infoHashBuffer":{"type":"Buffer","data":[171,158,88,98,86,248,61,54,36,21,160,175,118,110,40,69,74,124,237,65]},"announce":[],"urlList":[]}}