{"title":"Birdman.of.Alcatraz.1962.720p.WEB-DL.H264-ViGi [PublicHD]","uid":9003961,"size":4572131160,"categoryP":"video","categoryS":"hd___movies","magnet":"?xt=urn:btih:db3c24b64451704ddb945a8f9af318764ce33ae7&amp;dn=Birdman.of.Alcatraz.1962.720p.WEB-DL.H264-ViGi+%5BPublicHD%5D&amp;tr=udp%3A%2F%2Ftracker.openbittorrent.com%3A80&amp;tr=udp%3A%2F%2Fopen.demonii.com%3A1337&amp;tr=udp%3A%2F%2Ftracker.coppersurfer.tk%3A6969&amp;tr=udp%3A%2F%2Fexodus.desync.com%3A6969","seeders":2,"leechers":3,"uploader":"aoloffline","files":-1,"time":1380998730,"description":"\n                PublicHD - High-Definition Bittorrent Community\n      \n              ----------------------------------------------------\n\nBirdman.of.Alcatraz.1962.720p.WEB-DL.H264-ViGi [PublicHD]\n &lt;a href=&quot;\nhttp://www.imdb.com/title/tt0055798/&quot; rel=&quot;nofollow&quot; target=&quot;_NEW&quot;&gt;\nhttp://www.imdb.com/title/tt0055798/&lt;/a&gt;\n\nLength..............: 2h 22mn\nVideo...............: 960x718 (X264 @ 25.000fps)\nBitrate.............: 4277Kbps\nAudio...............: AC3 192 Kbps\nLanguage............: English\nSubtitles...........: English\nGenre ..............: Biography | Drama\n\n\nS C R E E N S :\n &lt;a href=&quot;\nhttp://someimage.com/CsrI6Ne&quot; rel=&quot;nofollow&quot; target=&quot;_NEW&quot;&gt;\nhttp://someimage.com/CsrI6Ne&lt;/a&gt;\n &lt;a href=&quot;\nhttp://someimage.com/1TPYSWl&quot; rel=&quot;nofollow&quot; target=&quot;_NEW&quot;&gt;\nhttp://someimage.com/1TPYSWl&lt;/a&gt;\n &lt;a href=&quot;\nhttp://someimage.com/e1L9E9b&quot; rel=&quot;nofollow&quot; target=&quot;_NEW&quot;&gt;\nhttp://someimage.com/e1L9E9b&lt;/a&gt;\n &lt;a href=&quot;\nhttp://someimage.com/WSfrHnN&quot; rel=&quot;nofollow&quot; target=&quot;_NEW&quot;&gt;\nhttp://someimage.com/WSfrHnN&lt;/a&gt;\n &lt;a href=&quot;\nhttp://someimage.com/zh8VWUj&quot; rel=&quot;nofollow&quot; target=&quot;_NEW&quot;&gt;\nhttp://someimage.com/zh8VWUj&lt;/a&gt;\n\n\n","torrent":{"xt":"urn:btih:db3c24b64451704ddb945a8f9af318764ce33ae7","amp;dn":"Birdman.of.Alcatraz.1962.720p.WEB-DL.H264-ViGi+%5BPublicHD%5D","amp;tr":["udp%3A%2F%2Ftracker.openbittorrent.com%3A80","udp%3A%2F%2Fopen.demonii.com%3A1337","udp%3A%2F%2Ftracker.coppersurfer.tk%3A6969","udp%3A%2F%2Fexodus.desync.com%3A6969"],"infoHash":"db3c24b64451704ddb945a8f9af318764ce33ae7","infoHashBuffer":{"type":"Buffer","data":[219,60,36,182,68,81,112,77,219,148,90,143,154,243,24,118,76,227,58,231]},"announce":[],"urlList":[]}}