{"title":"Blue Scholars - OOF! EP [320 kbps]","uid":5110474,"size":118330105,"categoryP":"audio","categoryS":"music","magnet":"?xt=urn:btih:dc65bce78362ba8a56c1e7b47a08529101a3e5a3&amp;dn=Blue+Scholars+-+OOF%21+EP+%5B320+kbps%5D&amp;tr=udp%3A%2F%2Ftracker.openbittorrent.com%3A80&amp;tr=udp%3A%2F%2Fopen.demonii.com%3A1337&amp;tr=udp%3A%2F%2Ftracker.coppersurfer.tk%3A6969&amp;tr=udp%3A%2F%2Fexodus.desync.com%3A6969","seeders":2,"leechers":0,"uploader":"jakemo40","files":11,"time":1254698234,"description":"OOF! EP is the sixth release by Blue Scholars. It is also their fourth EP and second EP that is available in hard copy format. It was released on August 25, 2009.\n\nThe EP received a limited edition run of 808 physical CDs which were made available online, at the Seattle release party, at CaffÃƒÂ© Vita locations in Seattle, and at IN4MATION Ward in Honolulu. A music video for the track &quot;HI-808&quot; was filmed in Hawaii.\n &lt;a href=&quot;\nhttp://bluescholars.com/&quot; rel=&quot;nofollow&quot; target=&quot;_NEW&quot;&gt;\nhttp://bluescholars.com/&lt;/a&gt;","torrent":{"xt":"urn:btih:dc65bce78362ba8a56c1e7b47a08529101a3e5a3","amp;dn":"Blue+Scholars+-+OOF%21+EP+%5B320+kbps%5D","amp;tr":["udp%3A%2F%2Ftracker.openbittorrent.com%3A80","udp%3A%2F%2Fopen.demonii.com%3A1337","udp%3A%2F%2Ftracker.coppersurfer.tk%3A6969","udp%3A%2F%2Fexodus.desync.com%3A6969"],"infoHash":"dc65bce78362ba8a56c1e7b47a08529101a3e5a3","infoHashBuffer":{"type":"Buffer","data":[220,101,188,231,131,98,186,138,86,193,231,180,122,8,82,145,1,163,229,163]},"announce":[],"urlList":[]}}