{"title":"A Quick Word With Beth Moore - 59 Sermons","uid":7275444,"size":57362752,"categoryP":"audio","categoryS":"music","magnet":"?xt=urn:btih:dc7de805a040f1429d57eb135ed806358c4462bc&amp;dn=A+Quick+Word+With+Beth+Moore+-+59+Sermons&amp;tr=udp%3A%2F%2Ftracker.openbittorrent.com%3A80&amp;tr=udp%3A%2F%2Fopen.demonii.com%3A1337&amp;tr=udp%3A%2F%2Ftracker.coppersurfer.tk%3A6969&amp;tr=udp%3A%2F%2Fexodus.desync.com%3A6969","seeders":2,"leechers":0,"uploader":"TorrentTracts","files":59,"time":1337265581,"description":"-----------------------------------------------------------\nA QUICK WORD WITH BETH MOORE - 59 SERMONS\n-----------------------------------------------------------\n\nBeth Moore is an American evangelist, author, and teacher. Moore founded Living Proof Ministries, a biblically-based organization for women, in 1994. It is based in Houston, Texas, and it primarily focuses on aiding women who desire to model their lives on evangelical Christian principles.\n\nThis torrent contains 59 very short messages with each running for about two minutes in length.  Details of all 59 topics can be found in the thread further below.\n\nGod Bless,\nTorrentTracts - May 2012\n","torrent":{"xt":"urn:btih:dc7de805a040f1429d57eb135ed806358c4462bc","amp;dn":"A+Quick+Word+With+Beth+Moore+-+59+Sermons","amp;tr":["udp%3A%2F%2Ftracker.openbittorrent.com%3A80","udp%3A%2F%2Fopen.demonii.com%3A1337","udp%3A%2F%2Ftracker.coppersurfer.tk%3A6969","udp%3A%2F%2Fexodus.desync.com%3A6969"],"infoHash":"dc7de805a040f1429d57eb135ed806358c4462bc","infoHashBuffer":{"type":"Buffer","data":[220,125,232,5,160,64,241,66,157,87,235,19,94,216,6,53,140,68,98,188]},"announce":[],"urlList":[]}}