{"title":"Grand Magus - The Hunt (Limited Edition) - 2012","uid":7297971,"size":139540313,"categoryP":"audio","categoryS":"music","magnet":"?xt=urn:btih:e7399d27e6ff5aed2dfa0e36b11a17d0a5c37286&amp;dn=Grand+Magus+-+The+Hunt+%28Limited+Edition%29+-+2012&amp;tr=udp%3A%2F%2Ftracker.openbittorrent.com%3A80&amp;tr=udp%3A%2F%2Fopen.demonii.com%3A1337&amp;tr=udp%3A%2F%2Ftracker.coppersurfer.tk%3A6969&amp;tr=udp%3A%2F%2Fexodus.desync.com%3A6969","seeders":2,"leechers":0,"uploader":"UGATeam","files":13,"time":1337905237,"description":" Downloaded from Rockbox(More details about the band there also).\nIf you like this,support the band buy the cd.Also seed it as much\nyou can.Cheers-horns up and many thanks to the original uploader!!!!","torrent":{"xt":"urn:btih:e7399d27e6ff5aed2dfa0e36b11a17d0a5c37286","amp;dn":"Grand+Magus+-+The+Hunt+%28Limited+Edition%29+-+2012","amp;tr":["udp%3A%2F%2Ftracker.openbittorrent.com%3A80","udp%3A%2F%2Fopen.demonii.com%3A1337","udp%3A%2F%2Ftracker.coppersurfer.tk%3A6969","udp%3A%2F%2Fexodus.desync.com%3A6969"],"infoHash":"e7399d27e6ff5aed2dfa0e36b11a17d0a5c37286","infoHashBuffer":{"type":"Buffer","data":[231,57,157,39,230,255,90,237,45,250,14,54,177,26,23,208,165,195,114,134]},"announce":[],"urlList":[]}}