{"title":"The Nut Job (2014) BR2DVD NTSC DD5.1 NL Subs [NLU002]","uid":9916614,"size":4529998010,"categoryP":"video","categoryS":"movies_dvdr","magnet":"?xt=urn:btih:ed115a950c4181102ed6f815734fd2bc999cc282&amp;dn=The+Nut+Job+%282014%29+BR2DVD+NTSC+DD5.1+NL+Subs+%5BNLU002%5D&amp;tr=udp%3A%2F%2Ftracker.openbittorrent.com%3A80&amp;tr=udp%3A%2F%2Fopen.demonii.com%3A1337&amp;tr=udp%3A%2F%2Ftracker.coppersurfer.tk%3A6969&amp;tr=udp%3A%2F%2Fexodus.desync.com%3A6969","seeders":2,"leechers":0,"uploader":"NLUPPER002","files":20,"time":1396949590,"description":"The Nut Job (2014) BR2DVD NTSC DD5.1 NL Subs [NLU002]\n.\n[URL=https://imageshack.com/i/nqtwdvj][IMG]http://imagizer.imageshack.us/v2/xq90/854/twdv.jpg[/IMG][/URL]\n.\nPG- 13   85 min  -  Animation | Adventure | Comedy  -  17 January 2014 (Canada) \nRated PG for mild action and rude humor\n. &lt;a href=&quot;\nhttp://www.imdb.com/title/tt1821658/&quot; rel=&quot;nofollow&quot; target=&quot;_NEW&quot;&gt;\nhttp://www.imdb.com/title/tt1821658/&lt;/a&gt;\n. &lt;a href=&quot;\nhttp://www.moviemeter.nl/film/87140&quot; rel=&quot;nofollow&quot; target=&quot;_NEW&quot;&gt;\nhttp://www.moviemeter.nl/film/87140&lt;/a&gt;\n.\nPLOT\n.\nAn incorrigibly self-serving exiled squirrel finds himself helping his former park brethren raid a nut store to survive, that is also the front for a human gang's bank robbery.\n.\nSource: 720p-SPARKS\nFormat: DVD5\nVideo: NTSC\nAudio: English DD.1\nSubtitles: Dutch. White and Yellow\nNL Vertaling: QoQ-TEAM\n.\nEnjoy","torrent":{"xt":"urn:btih:ed115a950c4181102ed6f815734fd2bc999cc282","amp;dn":"The+Nut+Job+%282014%29+BR2DVD+NTSC+DD5.1+NL+Subs+%5BNLU002%5D","amp;tr":["udp%3A%2F%2Ftracker.openbittorrent.com%3A80","udp%3A%2F%2Fopen.demonii.com%3A1337","udp%3A%2F%2Ftracker.coppersurfer.tk%3A6969","udp%3A%2F%2Fexodus.desync.com%3A6969"],"infoHash":"ed115a950c4181102ed6f815734fd2bc999cc282","infoHashBuffer":{"type":"Buffer","data":[237,17,90,149,12,65,129,16,46,214,248,21,115,79,210,188,153,156,194,130]},"announce":[],"urlList":[]}}