{"title":"La Grande Bellezza (The Great Beauty) 2013 BDRemux 1080p GORESEW","uid":9720524,"size":36557953713,"categoryP":"video","categoryS":"hd___movies","magnet":"?xt=urn:btih:f59cd64aa450037c5220c933cd0d74a84a2e0d5c&amp;dn=La+Grande+Bellezza+%28The+Great+Beauty%29+2013+BDRemux+1080p+GORESEW&amp;tr=udp%3A%2F%2Ftracker.openbittorrent.com%3A80&amp;tr=udp%3A%2F%2Fopen.demonii.com%3A1337&amp;tr=udp%3A%2F%2Ftracker.coppersurfer.tk%3A6969&amp;tr=udp%3A%2F%2Fexodus.desync.com%3A6969","seeders":2,"leechers":1,"uploader":"ABSTAIN","files":1,"time":1394227984,"description":"C:/GORESEWAGE/La Grande Bellezza (The Great Beauty) 2013 BDRemux 1080p GORESEWAGE.mkv\n  General\n    Unique ID : 239760017010560243091616714428802634566 (0xB4601980E0478E9CA7C8C38FBB0F9346)\n    Complete name : C:/GORESEWAGE/La Grande Bellezza (The Great Beauty) 2013 BDRemux 1080p GORESEWAGE.mkv\n    Format : Matroska\n    Format version : Version 4 / Version 2\n    File size : 34.0 GiB\n    Duration : 2h 20mn\n    Overall bit rate mode : Variable\n    Overall bit rate : 34.6 Mbps\n    Movie name : La Grande Bellezza (The Great Beauty) 2013 BDRemux 1080p GORESEWAGE\n    Encoded date : UTC 2014-03-07 15:23:32\n    Writing application : mkvmerge v6.8.0 ('Theme for Great Cities') 64bit built on Mar  2 2014 21:34:26\n    Writing library : libebml v1.3.0 + libmatroska v1.4.1\n    Attachment : Yes\n  Video #1\n    ID : 1\n    Format : AVC\n    Format/Info : Advanced Video Codec\n    Format profile : &lt;a class=&quot;__cf_email__&quot; href=&quot;/cdn-cgi/l/email-protection&quot; data-cfemail=&quot;b7ffded0dff7fb839986&quot;&gt;[email&amp;#160;protected]&lt;/a&gt;&lt;script cf-hash='f9e31' type=&quot;text/javascript&quot;&gt;\n/* &lt;![CDATA[ */!function(){try{var t=&quot;currentScript&quot;in document?document.currentScript:function(){for(var t=document.getElementsByTagName(&quot;script&quot;),e=t.length;e--;)if(t[e].getAttribute(&quot;cf-hash&quot;))return t[e]}();if(t&amp;&amp;t.previousSibling){var e,r,n,i,c=t.previousSibling,a=c.getAttribute(&quot;data-cfemail&quot;);if(a){for(e=&quot;&quot;,r=parseInt(a.substr(0,2),16),n=2;a.length-n;n+=2)i=parseInt(a.substr(n,2),16)^r,e+=String.fromCharCode(i);e=document.createTextNode(e),c.parentNode.replaceChild(e,c)}}}catch(u){}}();/* ]]&gt; */&lt;/script&gt;\n    Format settings, CABAC : Yes\n    Format settings, ReFrames : 4 frames\n    Format settings, GOP : M=3, N=18\n    Codec ID : V_MPEG4/ISO/AVC\n    Duration : 2h 20mn\n    Bit rate mode : Variable\n    Maximum bit rate : 38.0 Mbps\n    Width : 1 920 pixels\n    Height : 1 080 pixels\n    Display aspect ratio : 16:9\n    Frame rate mode : Constant\n    Frame rate : 24.000 fps\n    Standard : NTSC\n    Color space : YUV\n    Chroma subsampling : 4:2:0\n    Bit depth : 8 bits\n    Scan type : Progressive\n    Title : La Grande Bellezza (The Great Beauty) 2013 BDRemux 1080p GORESEWAGE\n    Language : Italian\n    Default : Yes\n    Forced : No\n    Color primaries : BT.709\n    Transfer characteristics : BT.709\n    Matrix coefficients : BT.709\n  Audio #2\n    ID : 2\n    Format : AC-3\n    Format/Info : Audio Coding 3\n    Mode extension : CM (complete main)\n    Format settings, Endianness : Big\n    Codec ID : A_AC3\n    Duration : 2h 20mn\n    Bit rate mode : Constant\n    Bit rate : 448 Kbps\n    Channel count : 6 channels\n    Channel positions : Front: L C R, Side: L R, LFE\n    Sampling rate : 48.0 KHz\n    Bit depth : 16 bits\n    Compression mode : Lossy\n    Stream size : 451 MiB (1%)\n    Title : MVO DVD R5\n    Language : Russian\n    Default : Yes\n    Forced : No\n  Audio #3\n    ID : 3\n    Format : DTS\n    Format/Info : Digital Theater Systems\n    Format profile : MA / Core\n    Mode : 16\n    Format settings, Endianness : Big\n    Codec ID : A_DTS\n    Duration : 2h 20mn\n    Bit rate mode : Variable\n    Bit rate : Unknown / 1 509 Kbps\n    Channel count : 6 channels\n    Channel positions : Front: L C R, Side: L R, LFE\n    Sampling rate : 48.0 KHz\n    Bit depth : 16 bits\n    Compression mode : Lossless / Lossy\n    Title : Original\n    Language : Italian\n    Default : No\n    Forced : No\n  Text #4\n    ID : 4\n    Format : UTF-8\n    Codec ID : S_TEXT/UTF8\n    Codec ID/Info : UTF-8 Plain Text\n    Title : SDH\n    Language : Italian\n    Default : No\n    Forced : No\n  Text #5\n    ID : 5\n    Format : UTF-8\n    Codec ID : S_TEXT/UTF8\n    Codec ID/Info : UTF-8 Plain Text\n    Title : Full\n    Language : English\n    Default : No\n    Forced : No\n  Text #6\n    ID : 6\n    Format : UTF-8\n    Codec ID : S_TEXT/UTF8\n    Codec ID/Info : UTF-8 Plain Text\n    Title : Full\n    Language : German\n    Default : No\n    Forced : No\n  Text #7\n    ID : 7\n    Format : UTF-8\n    Codec ID : S_TEXT/UTF8\n    Codec ID/Info : UTF-8 Plain Text\n    Title : Full\n    Language : Greek\n    Default : No\n    Forced : No\n  Text #8\n    ID : 8\n    Format : UTF-8\n    Codec ID : S_TEXT/UTF8\n    Codec ID/Info : UTF-8 Plain Text\n    Title : Full BRA\n    Language : Portuguese\n    Default : No\n    Forced : No\n  Text #9\n    ID : 9\n    Format : UTF-8\n    Codec ID : S_TEXT/UTF8\n    Codec ID/Info : UTF-8 Plain Text\n    Title : Full\n    Language : Romanian\n    Default : No\n    Forced : No\n  Text #10\n    ID : 10\n    Format : UTF-8\n    Codec ID : S_TEXT/UTF8\n    Codec ID/Info : UTF-8 Plain Text\n    Title : Full\n    Language : Serbian\n    Default : No\n    Forced : No\n  Text #11\n    ID : 11\n    Format : UTF-8\n    Codec ID : S_TEXT/UTF8\n    Codec ID/Info : UTF-8 Plain Text\n    Title : Full\n    Language : Slovenian\n    Default : No\n    Forced : No\n  Text #12\n    ID : 12\n    Format : UTF-8\n    Codec ID : S_TEXT/UTF8\n    Codec ID/Info : UTF-8 Plain Text\n    Title : Full\n    Language : Spanish\n    Default : No\n    Forced : No\n  Text #13\n    ID : 13\n    Format : UTF-8\n    Codec ID : S_TEXT/UTF8\n    Codec ID/Info : UTF-8 Plain Text\n    Title : Full\n    Language : Turkish\n    Default : No\n    Forced : No\n  Menu\n    00:00:00.000 : :00:00:00.000\n    00:12:38.833 : :00:12:38.833\n    00:21:04.625 : :00:21:04.625\n    00:26:05.208 : :00:26:05.208\n    00:42:57.917 : :00:42:57.917\n    00:54:46.042 : :00:54:46.042\n    01:10:15.000 : :01:10:15.000\n    01:22:31.750 : :01:22:31.750\n    01:31:05.417 : :01:31:05.417\n    01:45:46.417 : :01:45:46.417\n    01:54:50.833 : :01:54:50.833\n    02:07:58.833 : :02:07:58.833","torrent":{"xt":"urn:btih:f59cd64aa450037c5220c933cd0d74a84a2e0d5c","amp;dn":"La+Grande+Bellezza+%28The+Great+Beauty%29+2013+BDRemux+1080p+GORESEW","amp;tr":["udp%3A%2F%2Ftracker.openbittorrent.com%3A80","udp%3A%2F%2Fopen.demonii.com%3A1337","udp%3A%2F%2Ftracker.coppersurfer.tk%3A6969","udp%3A%2F%2Fexodus.desync.com%3A6969"],"infoHash":"f59cd64aa450037c5220c933cd0d74a84a2e0d5c","infoHashBuffer":{"type":"Buffer","data":[245,156,214,74,164,80,3,124,82,32,201,51,205,13,116,168,74,46,13,92]},"announce":[],"urlList":[]}}