{"title":"[HorribleSubs] Witch Craft Works - 05 [480p].mkv","uid":9572295,"size":153502678,"categoryP":"video","categoryS":"tv_shows","magnet":"?xt=urn:btih:fd22e87f0f523b2d0630738d27750a89e6598543&amp;dn=%5BHorribleSubs%5D+Witch+Craft+Works+-+05+%5B480p%5D.mkv&amp;tr=udp%3A%2F%2Ftracker.openbittorrent.com%3A80&amp;tr=udp%3A%2F%2Fopen.demonii.com%3A1337&amp;tr=udp%3A%2F%2Ftracker.coppersurfer.tk%3A6969&amp;tr=udp%3A%2F%2Fexodus.desync.com%3A6969","seeders":2,"leechers":0,"uploader":"darkj6","files":1,"time":1391645038,"description":" ______   _______  ______    ___   _      ___  --------|\n|      | |   _   ||    _ |  |   | | |    |   ||   |----|    \n|  _    ||  |_|  ||   | ||  |   |_| |    |   ||   |___ \n| | |   ||       ||   |_||_ |      _|    |   ||    _  |\n| |_|   ||       ||    __  ||     |_  ___|   ||   | | |\n|       ||   _   ||   |  | ||    _  ||       ||   |_| |\n|______| |__| |__||___|  |_||___| |_||_______||_______|","torrent":{"xt":"urn:btih:fd22e87f0f523b2d0630738d27750a89e6598543","amp;dn":"%5BHorribleSubs%5D+Witch+Craft+Works+-+05+%5B480p%5D.mkv","amp;tr":["udp%3A%2F%2Ftracker.openbittorrent.com%3A80","udp%3A%2F%2Fopen.demonii.com%3A1337","udp%3A%2F%2Ftracker.coppersurfer.tk%3A6969","udp%3A%2F%2Fexodus.desync.com%3A6969"],"infoHash":"fd22e87f0f523b2d0630738d27750a89e6598543","infoHashBuffer":{"type":"Buffer","data":[253,34,232,127,15,82,59,45,6,48,115,141,39,117,10,137,230,89,133,67]},"announce":[],"urlList":[]}}