{"title":"A Thorn For Every Heart - Things Aren't So Beautiful Now 2004","uid":3555532,"size":59053133,"categoryP":"audio","categoryS":"music","magnet":"?xt=urn:btih:ff55e35f8b9bbfe6e78b8ebc31843c4254d5d664&amp;dn=A+Thorn+For+Every+Heart+-+Things+Aren%5C%27t+So+Beautiful+Now+2004&amp;tr=udp%3A%2F%2Ftracker.openbittorrent.com%3A80&amp;tr=udp%3A%2F%2Fopen.demonii.com%3A1337&amp;tr=udp%3A%2F%2Ftracker.coppersurfer.tk%3A6969&amp;tr=udp%3A%2F%2Fexodus.desync.com%3A6969","seeders":2,"leechers":0,"uploader":"Make_My_Day","files":10,"time":1163263249,"description":"The album highlights innate songwriting skill, solid musical chemistry and a united vision in sound. It embodies elements of ATFEH&amp;#039;s favorite hardcore, emo and punk bands.\n\n\nTRACKS\n\n1. 99 With An Anchor - \n2. February\n3. A Night To Remember, A Morning To Forget\n4. Next of Kin\n5. The Prediction\n6. Street Car\n7. Summer So Bleak\n8. Pretty When You Cry\n9. Things Aren&amp;#039;t So Beautiful Now (Part 1)\n10. Things Aren&amp;#039;t So Beautiful Now (Part 2)","torrent":{"xt":"urn:btih:ff55e35f8b9bbfe6e78b8ebc31843c4254d5d664","amp;dn":"A+Thorn+For+Every+Heart+-+Things+Aren%5C%27t+So+Beautiful+Now+2004","amp;tr":["udp%3A%2F%2Ftracker.openbittorrent.com%3A80","udp%3A%2F%2Fopen.demonii.com%3A1337","udp%3A%2F%2Ftracker.coppersurfer.tk%3A6969","udp%3A%2F%2Fexodus.desync.com%3A6969"],"infoHash":"ff55e35f8b9bbfe6e78b8ebc31843c4254d5d664","infoHashBuffer":{"type":"Buffer","data":[255,85,227,95,139,155,191,230,231,139,142,188,49,132,60,66,84,213,214,100]},"announce":[],"urlList":[]}}